{"ID":10083,"SkinName":"Gray","CharacterName":"Male","EyesName":"Green","MaskName":"Indian","ItemName":"Golden Toilet Paper","Link":"https://thehashmasks.com/detail/10083","SkinId":4658,"CharacterId":8660,"EyesId":2634,"MaskId":802,"ItemId":77,"SkinP":0.2842844065,"CharacterP":0.5285321941,"EyesP":0.1607567897,"MaskP":0.04894720781,"ItemP":0.004699420201,"TotalP":0.00001954397837,"SkinPPercentileRank":11726,"CharacterPPercentileRank":7724,"EyesPPercentileRank":2798,"MaskPPercentileRank":1312,"ItemPPercentileRank":0,"TotalPPercentileRank":640,"ImageLink":"https://ipfs.io/ipfs/QmPR2fpWF8HaZYC5sTaZuT247Yo433hu93NqV89cEqqVNg"}