{"ID":11227,"SkinName":"Blue","CharacterName":"Male","EyesName":"Freak","MaskName":"Mexican","ItemName":"No Item","Link":"https://thehashmasks.com/detail/11227","SkinId":1292,"CharacterId":8660,"EyesId":435,"MaskId":2476,"ItemId":14533,"SkinP":0.07885260909,"CharacterP":0.5285321941,"EyesP":0.02654867257,"MaskP":0.1511138236,"ItemP":0.8869697894,"TotalP":0.001880733585,"SkinPPercentileRank":922,"CharacterPPercentileRank":7724,"EyesPPercentileRank":146,"MaskPPercentileRank":13908,"ItemPPercentileRank":1851,"TotalPPercentileRank":4022,"ImageLink":"https://ipfs.io/ipfs/QmQpYoQ1g7QJQfjcmvBTGjW3QoQs7bGxCMPt11ZUzjiU6f"}