{"ID":11687,"SkinName":"Gray","CharacterName":"Female","EyesName":"Green","MaskName":"Indian","ItemName":"Toilet Paper","Link":"https://thehashmasks.com/detail/11687","SkinId":4658,"CharacterId":5480,"EyesId":2634,"MaskId":802,"ItemId":395,"SkinP":0.2842844065,"CharacterP":0.3344522429,"EyesP":0.1607567897,"MaskP":0.04894720781,"ItemP":0.02410741532,"TotalP":0.00006344275152,"SkinPPercentileRank":11726,"CharacterPPercentileRank":2244,"EyesPPercentileRank":2798,"MaskPPercentileRank":1312,"ItemPPercentileRank":1006,"TotalPPercentileRank":1235,"ImageLink":"https://ipfs.io/ipfs/QmRh7iwiQirtTfv4dsaT1GfXftsE7PYkdTxiyGUWkMCmiV"}