{"ID":14633,"SkinName":"Blue","CharacterName":"Male","EyesName":"Blue","MaskName":"Steampunk","ItemName":"Toilet Paper","Link":"https://thehashmasks.com/detail/14633","SkinId":1292,"CharacterId":8660,"EyesId":3532,"MaskId":229,"ItemId":395,"SkinP":0.07885260909,"CharacterP":0.5285321941,"EyesP":0.215563015,"MaskP":0.01397619774,"ItemP":0.02410741532,"TotalP":0.00003838710689,"SkinPPercentileRank":922,"CharacterPPercentileRank":7724,"EyesPPercentileRank":5432,"MaskPPercentileRank":11,"ItemPPercentileRank":1006,"TotalPPercentileRank":983,"ImageLink":"https://ipfs.io/ipfs/QmPRiRzvdHRhGmeC1XSQKcsKxW6jLPfDv5TRMe3CHxZ4qc"}