{"ID":15689,"SkinName":"Dark","CharacterName":"Female","EyesName":"Heterochromatic","MaskName":"Animal","ItemName":"Shadow Monkey","Link":"https://thehashmasks.com/detail/15689","SkinId":3784,"CharacterId":5480,"EyesId":134,"MaskId":2061,"ItemId":233,"SkinP":0.2309429356,"CharacterP":0.3344522429,"EyesP":0.008178211779,"MaskP":0.1257857797,"ItemP":0.01422032347,"TotalP":0.000004892529881,"SkinPPercentileRank":3690,"CharacterPPercentileRank":2244,"EyesPPercentileRank":12,"MaskPPercentileRank":7444,"ItemPPercentileRank":77,"TotalPPercentileRank":234,"ImageLink":"https://ipfs.io/ipfs/QmQhTZ9b72b3Ge5jgtHR7FFm8hHjtTt1gzEn8BtcRd6xnz"}