{"ID":3106,"SkinName":"Dark","CharacterName":"Male","EyesName":"Blue","MaskName":"Animal","ItemName":"Toilet Paper","Link":"https://thehashmasks.com/detail/3106","SkinId":3784,"CharacterId":8660,"EyesId":3532,"MaskId":2061,"ItemId":395,"SkinP":0.2309429356,"CharacterP":0.5285321941,"EyesP":0.215563015,"MaskP":0.1257857797,"ItemP":0.02410741532,"TotalP":0.000345483962,"SkinPPercentileRank":3690,"CharacterPPercentileRank":7724,"EyesPPercentileRank":5432,"MaskPPercentileRank":7444,"ItemPPercentileRank":1006,"TotalPPercentileRank":2432,"ImageLink":"https://ipfs.io/ipfs/QmTNGtFtf4QHfH9cq4e9XSW5Xmd2b7j5x9FfqK2P1AJWqT"}