{"ID":4073,"SkinName":"Blue","CharacterName":"Male","EyesName":"Dark","MaskName":"African","ItemName":"Bottle","Link":"https://thehashmasks.com/detail/4073","SkinId":1292,"CharacterId":8660,"EyesId":7420,"MaskId":967,"ItemId":377,"SkinP":0.07885260909,"CharacterP":0.5285321941,"EyesP":0.4528532194,"MaskP":0.05901739396,"ItemP":0.02300884956,"TotalP":0.0003250153247,"SkinPPercentileRank":922,"CharacterPPercentileRank":7724,"EyesPPercentileRank":8964,"MaskPPercentileRank":3924,"ItemPPercentileRank":629,"TotalPPercentileRank":2404,"ImageLink":"https://ipfs.io/ipfs/QmT8eqXAdh2KxVEoYjXAhHh9JgyJndsidYiYpLnE5568cr"}