{"ID":4738,"SkinName":"Light","CharacterName":"Male","EyesName":"Green","MaskName":"Crayon","ItemName":"Shadow Monkey","Link":"https://thehashmasks.com/detail/4738","SkinId":4252,"CharacterId":8660,"EyesId":2634,"MaskId":490,"ItemId":233,"SkinP":0.2595056454,"CharacterP":0.5285321941,"EyesP":0.1607567897,"MaskP":0.02990540128,"ItemP":0.01422032347,"TotalP":0.00003613265554,"SkinPPercentileRank":7474,"CharacterPPercentileRank":7724,"EyesPPercentileRank":2798,"MaskPPercentileRank":822,"ItemPPercentileRank":77,"TotalPPercentileRank":958,"ImageLink":"https://ipfs.io/ipfs/QmUmkD4yG74q1hVdF7uGQheRSEtx1Q4Cj1tY2YPp4TWQDk"}