{"ID":5979,"SkinName":"Light","CharacterName":"Male","EyesName":"Green","MaskName":"Animal","ItemName":"No Item","Link":"https://thehashmasks.com/detail/5979","SkinId":4252,"CharacterId":8660,"EyesId":2634,"MaskId":2061,"ItemId":14533,"SkinP":0.2595056454,"CharacterP":0.5285321941,"EyesP":0.1607567897,"MaskP":0.1257857797,"ItemP":0.8869697894,"TotalP":0.009479406453,"SkinPPercentileRank":7474,"CharacterPPercentileRank":7724,"EyesPPercentileRank":2798,"MaskPPercentileRank":7444,"ItemPPercentileRank":1851,"TotalPPercentileRank":8067,"ImageLink":"https://ipfs.io/ipfs/QmSAjYEWHntHKXzX4AUraDxxo6ER978XHLMawV6v6Y1pEU"}