{"ID":6249,"SkinName":"Gray","CharacterName":"Male","EyesName":"Freak","MaskName":"Steampunk","ItemName":"No Item","Link":"https://thehashmasks.com/detail/6249","SkinId":4658,"CharacterId":8660,"EyesId":435,"MaskId":229,"ItemId":14533,"SkinP":0.2842844065,"CharacterP":0.5285321941,"EyesP":0.02654867257,"MaskP":0.01397619774,"ItemP":0.8869697894,"TotalP":0.0001739450691,"SkinPPercentileRank":11726,"CharacterPPercentileRank":7724,"EyesPPercentileRank":146,"MaskPPercentileRank":11,"ItemPPercentileRank":1851,"TotalPPercentileRank":2072,"ImageLink":"https://ipfs.io/ipfs/QmeDwTyCgKikaRBQxYbDG1MV7fQrS8M4HCwzgriFp8J5SN"}