{"ID":7771,"SkinName":"Gold","CharacterName":"Golden Robot","EyesName":"Glass","MaskName":"Mexican","ItemName":"Golden Toilet Paper","Link":"https://thehashmasks.com/detail/7771","SkinId":165,"CharacterId":165,"EyesId":1626,"MaskId":2476,"ItemId":77,"SkinP":0.01007018615,"CharacterP":0.01007018615,"EyesP":0.09923710711,"MaskP":0.1511138236,"ItemP":0.004699420201,"TotalP":7.096759178e-7,"SkinPPercentileRank":166,"CharacterPPercentileRank":12,"EyesPPercentileRank":1172,"MaskPPercentileRank":13908,"ItemPPercentileRank":0,"TotalPPercentileRank":55,"ImageLink":"https://ipfs.io/ipfs/QmbeHfDGR3JCGzFWg3pZKrsv5kmb86Ub4AvAKKVi2y8kzG"}