{"ID":9876,"SkinName":"Dark","CharacterName":"Female","EyesName":"Blue","MaskName":"Steampunk","ItemName":"Golden Toilet Paper","Link":"https://thehashmasks.com/detail/9876","SkinId":3784,"CharacterId":5480,"EyesId":3532,"MaskId":229,"ItemId":77,"SkinP":0.2309429356,"CharacterP":0.3344522429,"EyesP":0.215563015,"MaskP":0.01397619774,"ItemP":0.004699420201,"TotalP":0.000004735236537,"SkinPPercentileRank":3690,"CharacterPPercentileRank":2244,"EyesPPercentileRank":5432,"MaskPPercentileRank":11,"ItemPPercentileRank":0,"TotalPPercentileRank":220,"ImageLink":"https://ipfs.io/ipfs/QmZbANCknGvtax9gGb2XMQLCZ5iSFUp9LCwgo53m9nTbSw"}